leantext/__init__.py
leantext/leantext.pypy310-pp73-arm-linux-gnu.so
leantext-1.1.0.dist-info/METADATA
leantext-1.1.0.dist-info/WHEEL
leantext_engine.py
leantext-1.1.0.dist-info/RECORD
